labelpandas/__init__.py
labelpandas/client.py
labelpandas/connector.py
labelpandas/load_local_files.py
labelpandas/uploader.py
labelpandas-0.1.39.dist-info/METADATA
labelpandas-0.1.39.dist-info/WHEEL
labelpandas-0.1.39.dist-info/top_level.txt
labelpandas-0.1.39.dist-info/RECORD
