Metadata-Version: 2.1
Name: labelpandas
Version: 0.1.39
Summary: Labelbox Connector for Pandas
Home-page: https://github.com/Labelbox/labelpandas
Author: Labelbox
Author-email: raphael@labelbox.com
Requires-Dist: labelbox[data]
Requires-Dist: labelbase
Requires-Dist: packaging
